.project
.pydevproject
LICENSE.txt
README.txt
distribute_setup.py
setup.cfg
setup.py
nosango/__init__.py
nosango/__version__.py
nosango/cases.py
nosango/models.py
nosango/plugin.py
nosango/storage.py
nosango/tools.py
nosango.egg-info/PKG-INFO
nosango.egg-info/SOURCES.txt
nosango.egg-info/dependency_links.txt
nosango.egg-info/entry_points.txt
nosango.egg-info/not-zip-safe
nosango.egg-info/requires.txt
nosango.egg-info/top_level.txt
nosango/management/__init__.py
nosango/management/commands/__init__.py
nosango/management/commands/restore.py
nosango/management/commands/truncate.py
tests/test_nosango/__init__.py
tests/test_nosango/test_tools.py
tests/test_nosango/test_tools/1/foo/toto.dat
tests/test_nosango/test_tools/2/toto.dat
tests/test_nosango/test_tools/2/foo/toto.dat