Metadata-Version: 1.0
Name: nosango
Version: 0.4
Summary: A Django test plug-in for Nose.
Home-page: http://code.google.com/p/nosango/
Author: ShiningPanda
Author-email: dev@shiningpanda.com
License: GNU AGPLv3
Download-URL: http://pypi.python.org/pypi/nosango/
Platform: UNKNOWN
Classifier: Development Status :: 4 - Beta
Classifier: Environment :: Plugins
Classifier: Framework :: Django
Classifier: Intended Audience :: Developers
Classifier: Natural Language :: English
Classifier: Operating System :: OS Independent
Classifier: Programming Language :: Python
Classifier: Topic :: Software Development :: Testing
